PyNaCl-1.2.1.dist-info/top_level.txt
PyNaCl-1.2.1.dist-info/RECORD
PyNaCl-1.2.1.dist-info/WHEEL
PyNaCl-1.2.1.dist-info/METADATA
nacl/public.py
nacl/signing.py
nacl/secret.py
nacl/encoding.py
nacl/hash.py
nacl/utils.py
nacl/hashlib.py
nacl/__init__.py
nacl/exceptions.py
nacl/_sodium.abi3.so
nacl/bindings/crypto_hash.py
nacl/bindings/utils.py
nacl/bindings/crypto_sign.py
nacl/bindings/crypto_secretbox.py
nacl/bindings/sodium_core.py
nacl/bindings/__init__.py
nacl/bindings/crypto_scalarmult.py
nacl/bindings/crypto_box.py
nacl/bindings/crypto_shorthash.py
nacl/bindings/crypto_generichash.py
nacl/bindings/randombytes.py
nacl/bindings/crypto_pwhash.py
nacl/pwhash/_argon2.py
nacl/pwhash/argon2id.py
nacl/pwhash/__init__.py
nacl/pwhash/argon2i.py
nacl/pwhash/scrypt.py
