Metadata-Version: 2.0
Name: PyNaCl
Version: 1.2.1
Summary: Python binding to the Networking and Cryptography (NaCl) library
Home-page: https://github.com/pyca/pynacl/
Author: The PyNaCl developers
Author-email: cryptography-dev@python.org
License: Apache License 2.0
Platform: UNKNOWN
Classifier: Programming Language :: Python :: Implementation :: CPython
Classifier: Programming Language :: Python :: Implementation :: PyPy
Classifier: Programming Language :: Python :: 2
Classifier: Programming Language :: Python :: 2.7
Classifier: Programming Language :: Python :: 3
Classifier: Programming Language :: Python :: 3.4
Classifier: Programming Language :: Python :: 3.5
Classifier: Programming Language :: Python :: 3.6
Requires-Dist: six
Requires-Dist: cffi (>=1.4.1)
Provides-Extra: docs
Requires-Dist: sphinx (>=1.6.5); extra == 'docs'
Requires-Dist: sphinx-rtd-theme; extra == 'docs'
Provides-Extra: tests
Requires-Dist: pytest (!=3.3.0,>=3.2.1); extra == 'tests'
Requires-Dist: hypothesis (>=3.27.0); extra == 'tests'
